mpfp.cpython-311-darwin.so
mpfp-1.0.3.dist-info/RECORD
mpfp-1.0.3.dist-info/WHEEL
mpfp-1.0.3.dist-info/top_level.txt
mpfp-1.0.3.dist-info/METADATA
mpfp-1.0.3.dist-info/licenses/LICENSE
