Metadata-Version: 2.4
Name: mpfp
Version: 1.0.3
Summary: A small geometry processing package for mesh planarization
Home-page: https://github.com/AntonFlorey/mpfp
Author: Anton Florey
Author-email: anton.florey@googlemail.com
License: MIT
Keywords: mesh,planarization,optimization
Classifier: Programming Language :: C++
Classifier: Topic :: Multimedia :: Graphics :: 3D Modeling
Requires-Python: ~=3.11
License-File: LICENSE
Requires-Dist: numpy
Dynamic: license-file
